rtl/alu.sv
module alu (
    input [31:0] a,
    input [31:0] b,
    input [3:0] opcode,
    output logic [31:0] result,
    output logic zero
);

always_comb begin
    case (opcode)
    4'b0000: result = a + b;          // ADD
    4'b0001: result = a - b;          // SUB
    4'b0010: result = a & b;          // AND
    4'b0011: result = a | b;          // OR
    4'b0100: result = a ^ b;          // XOR
    4'b0101: result = a << b[4:0];   // SLL
    4'b0110: result = a >> b[4:0];   // SRL
    4'b0111: result = $signed(a) >>> b[4:0]; // SRA
    4'b1000: result = (a < b) ? 32'b1 : 32'b0; // SLT
    default: result = 32'b0;          // NOP
    endcase
end

assign zero = (result == 32'b0);
endmodule

top.sv
module regfile32 (
    input logic clk,
    input logic we,
    input logic [4:0] waddr,
    input logic [31:0] wdata,
    input logic [4:0] raddr1,
    output logic [31:0] rdata1,
    input logic [4:0] raddr2,
    output logic [31:0] rdata2
);

    logic [31:0] regs [0:31];

    always_comb begin
        rdata1 = (raddr1 != 5'd0) ? regs[raddr1] : 32'd0;
        rdata2 = (raddr2 != 5'd0) ? regs[raddr2] : 32'd0;
    end

    always_ff @(posedge clk) begin
        if (we && (waddr != 5'd0)) begin
            regs[waddr] <= wdata;
        end
    end
endmodule

module cpu_top (
    input clk,
    input reset_n,
    
    input logic imem_req_ready,
    input logic imem_resp_valid,
    input logic [31:0] imem_resp_data,
    output wire imem_req_valid,
    output wire [31:0] imem_req_addr,
    output wire imem_resp_ready,
    output logic [31:0] dbg_x1,
    output logic [31:0] dbg_x2,
    output logic [31:0] dbg_x3
);
    

logic [31:0] pc_current;
logic [31:0] pc_next;
logic pc_en;

pc_reg u_pc (
    .clk(clk),
    .reset_n(reset_n),
    .pc_en(pc_en),
    .pc_next(pc_next),
    .pc_current(pc_current)
);

fetch_stage u_fetch (
    .clk(clk),
    .reset_n(reset_n),
    .imem_req_ready(imem_req_ready),
    .imem_resp_valid(imem_resp_valid),
    .imem_resp_data(imem_resp_data),
    .pc_current(pc_current),
    .imem_req_valid(imem_req_valid),
    .imem_req_addr(imem_req_addr),
    .imem_resp_ready(imem_resp_ready)
);

logic imem_req_fire;
logic imem_resp_fire;   
assign imem_req_fire = imem_req_valid && imem_req_ready;
assign imem_resp_fire = imem_resp_valid && imem_resp_ready;

assign pc_next = pc_current + 32'd4;
assign pc_en = imem_resp_fire;

logic if_id_valid;
logic [31:0] if_id_inst;

logic consume;
assign consume = if_id_valid;

always_ff @(posedge clk) begin
    if (!reset_n) begin
        if_id_valid <= 1'b0;
        if_id_inst <= 32'b0;
    end else begin
        if (imem_resp_fire && (!if_id_valid || consume)) begin
            if_id_inst <= imem_resp_data;
        end
        if_id_valid <= (if_id_valid && !consume) ? 1'b1
                    : (imem_resp_fire ? 1'b1 : 1'b0);
    end
end

logic [6:0] opcode;
logic [4:0] rd;
logic [2:0] funct3;
logic [4:0] rs1;
logic [4:0] rs2;
logic [6:0] funct7;
logic [31:0] imm_i;
logic [4:0] shamt;

field_extractor u_dec (
    .instruction(if_id_inst),
    .opcode(opcode),
    .rd(rd),
    .funct3(funct3),
    .rs1(rs1),
    .rs2(rs2),
    .funct7(funct7),
    .imm_i(imm_i),
    .shamt(shamt)
);

logic [31:0] rs1_data;
logic [31:0] rs2_data;
logic wb_we;
logic [4:0] wb_rd;
logic [31:0] wb_data;

regfile32 u_rf (
    .clk(clk),
    .we(wb_we),
    .waddr(wb_rd),
    .wdata(wb_data),
    .raddr1(rs1),
    .rdata1(rs1_data),
    .raddr2(rs2),
    .rdata2(rs2_data)
);

assign dbg_x1 = u_rf.regs[1];
assign dbg_x2 = u_rf.regs[2];
assign dbg_x3 = u_rf.regs[3];

logic is_rtype, is_itype;
assign is_rtype = (opcode == 7'b0110011);
assign is_itype = (opcode == 7'b0010011);

logic op_add, op_sub, op_and, op_or, op_addi;
assign op_add = is_rtype && (funct3 == 3'b000) && (funct7 == 7'b0000000);
assign op_sub = is_rtype && (funct3 == 3'b000) && (funct7 == 7'b0100000);
assign op_and = is_rtype && (funct3 == 3'b111) && (funct7 == 7'b0000000);
assign op_or  = is_rtype && (funct3 == 3'b110) && (funct7 == 7'b0000000);
assign op_addi = is_itype && (funct3 == 3'b000);

logic [31:0] alu_in2;
assign alu_in2 = op_addi ? imm_i : rs2_data;

logic [3:0] alu_opcode;
assign alu_opcode =
    op_sub ? 4'b0001 :
    op_and ? 4'b0010 :
    op_or  ? 4'b0011 :
             4'b0000;

logic [31:0] alu_res;
logic alu_zero;

alu u_alu (
    .a(rs1_data),
    .b(alu_in2),
    .opcode(alu_opcode),
    .result(alu_res),
    .zero(alu_zero)
);

logic dec_wb_we;
assign dec_wb_we = op_add || op_sub || op_and || op_or || op_addi;

assign wb_we = if_id_valid && dec_wb_we;
assign wb_rd = rd;
assign wb_data = alu_res;

endmodule

dec.v
module field_extractor (
    input [31:0] instruction,
    output [6:0] opcode,
    output [4:0] rd,
    output [2:0] funct3,
    output [4:0] rs1,
    output [4:0] rs2,
    output [6:0] funct7,

    output [31:0] imm_i,
    output [4:0] shamt
);
    assign opcode = instruction[6:0];
    assign rd     = instruction[11:7];
    assign funct3 = instruction[14:12];
    assign rs1    = instruction[19:15];
    assign rs2    = instruction[24:20];
    assign funct7 = instruction[31:25];

    // I-type immediate extraction
    assign imm_i  = {{20{instruction[31]}}, instruction[31:20]}; // Sign-extend 12-bit immediate
    assign shamt  = instruction[24:20]; // Shift amount for shift instructions

endmodule

rtl/stages/fetch.sv
module pc_reg (
    input clk,
    input reset_n,
    input pc_en,
    input [31:0] pc_next,
    output logic [31:0] pc_current
);

    always_ff @(posedge clk) begin
        if (!reset_n)
            pc_current <= 32'b0; // Reset PC to 0
        else if (pc_en)
            pc_current <= pc_next; // Update PC
    end
endmodule

module fetch_stage(
  input  logic       clk,
  input  logic       reset_n,
  input  logic       imem_req_ready,
  input  logic       imem_resp_valid,
  input  logic [31:0] imem_resp_data,
  input  logic [31:0] pc_current,
  output logic       imem_req_valid,
  output logic [31:0] imem_req_addr,
  output logic       imem_resp_ready
);
  logic  imem_outstanding;

  assign imem_req_valid  = ~imem_outstanding;
  assign imem_req_addr   = pc_current;
  assign imem_resp_ready = 1'b1;

  logic imem_req_fire;
  assign imem_req_fire = imem_req_valid  & imem_req_ready;
  logic imem_resp_fire;
  assign imem_resp_fire = imem_resp_valid & imem_resp_ready;

  always_ff @(posedge clk) begin
  if (!reset_n) begin
    imem_outstanding <= 1'b0;
  end else begin
    if (imem_req_fire)  imem_outstanding <= 1'b1;
    if (imem_resp_fire) imem_outstanding <= 1'b0;
  end
end
endmodule

tb_cpu_top.sv
`timescale 1ns/1ps
module tb_cpu_top;
  logic clk = 0;
  logic reset_n = 0;

  logic imem_req_valid;
  logic [31:0] imem_req_addr;
  logic imem_req_ready = 1'b1;

  logic imem_resp_valid = 1'b0;
  logic [31:0] imem_resp_data = 32'd0;
  logic imem_resp_ready;

  logic [31:0] dbg_x1;
  logic [31:0] dbg_x2;
  logic [31:0] dbg_x3;

  cpu_top dut (
    .clk(clk),
    .reset_n(reset_n),
    .imem_req_ready(imem_req_ready),
    .imem_resp_valid(imem_resp_valid),
    .imem_resp_data(imem_resp_data),
    .imem_req_valid(imem_req_valid),
    .imem_req_addr(imem_req_addr),
    .imem_resp_ready(imem_resp_ready),
    .dbg_x1(dbg_x1),
    .dbg_x2(dbg_x2),
    .dbg_x3(dbg_x3)
  );

  initial begin
    forever #5 clk = ~clk;
  end

  logic [31:0] rom [0:255];
  integer i;

  initial begin
    for (i = 0; i < 256; i = i + 1) rom[i] = 32'h00000013;

    rom[0] = 32'h00500093; // addi x1, x0, 5
    rom[1] = 32'h00700113; // addi x2, x0, 7
    rom[2] = 32'h002081b3; // add  x3, x1, x2
    rom[3] = 32'h00000013; // nop

    $dumpfile("cpu.vcd");
    $dumpvars(0, tb_cpu_top);

    #1;
    reset_n = 0;
    #30;
    for (i = 0; i < 32; i = i + 1)
      dut.u_rf.regs[i] = 32'd0;
    reset_n = 1;

    #200;
    $display("x1=%h x2=%h x3=%h", dbg_x1, dbg_x2, dbg_x3);

    #500;
    $finish;
  end

  logic pending;
  logic [31:0] pending_addr;

  always_ff @(posedge clk) begin
    if (!reset_n) begin
      imem_resp_valid <= 1'b0;
      imem_resp_data  <= 32'd0;
      pending         <= 1'b0;
      pending_addr    <= 32'd0;
    end else begin
      imem_resp_valid <= 1'b0;

      if (pending) begin
        imem_resp_valid <= 1'b1;
        imem_resp_data  <= rom[pending_addr[9:2]];
        pending         <= 1'b0;
      end

      if (imem_req_valid && imem_req_ready) begin
        pending      <= 1'b1;
        pending_addr <= imem_req_addr;
      end
    end
  end
endmodule

cpu.vcd
$date
	Wed Jan 28 15:06:25 2026
$end
$version
	Icarus Verilog
$end
$timescale
	1ps
$end
$scope module tb_cpu_top $end
$var wire 1 ! imem_resp_ready $end
$var wire 1 " imem_req_valid $end
$var wire 32 # imem_req_addr [31:0] $end
$var wire 32 $ dbg_x3 [31:0] $end
$var wire 32 % dbg_x2 [31:0] $end
$var wire 32 & dbg_x1 [31:0] $end
$var reg 1 ' clk $end
$var reg 1 ( imem_req_ready $end
$var reg 32 ) imem_resp_data [31:0] $end
$var reg 1 * imem_resp_valid $end
$var reg 1 + pending $end
$var reg 32 , pending_addr [31:0] $end
$var reg 1 - reset_n $end
$var integer 32 . i [31:0] $end
$scope module dut $end
$var wire 1 ' clk $end
$var wire 1 / consume $end
$var wire 32 0 dbg_x1 [31:0] $end
$var wire 32 1 dbg_x2 [31:0] $end
$var wire 32 2 dbg_x3 [31:0] $end
$var wire 1 3 dec_wb_we $end
$var wire 1 4 imem_req_fire $end
$var wire 1 ( imem_req_ready $end
$var wire 32 5 imem_resp_data [31:0] $end
$var wire 1 6 imem_resp_fire $end
$var wire 1 ! imem_resp_ready $end
$var wire 1 * imem_resp_valid $end
$var wire 1 7 op_add $end
$var wire 1 8 op_addi $end
$var wire 1 9 op_and $end
$var wire 1 : op_or $end
$var wire 1 ; op_sub $end
$var wire 1 < pc_en $end
$var wire 1 - reset_n $end
$var wire 32 = wb_data [31:0] $end
$var wire 5 > wb_rd [4:0] $end
$var wire 1 ? wb_we $end
$var wire 5 @ shamt [4:0] $end
$var wire 32 A rs2_data [31:0] $end
$var wire 5 B rs2 [4:0] $end
$var wire 32 C rs1_data [31:0] $end
$var wire 5 D rs1 [4:0] $end
$var wire 5 E rd [4:0] $end
$var wire 32 F pc_next [31:0] $end
$var wire 32 G pc_current [31:0] $end
$var wire 7 H opcode [6:0] $end
$var wire 1 I is_rtype $end
$var wire 1 J is_itype $end
$var wire 32 K imm_i [31:0] $end
$var wire 1 " imem_req_valid $end
$var wire 32 L imem_req_addr [31:0] $end
$var wire 7 M funct7 [6:0] $end
$var wire 3 N funct3 [2:0] $end
$var wire 1 O alu_zero $end
$var wire 32 P alu_res [31:0] $end
$var wire 4 Q alu_opcode [3:0] $end
$var wire 32 R alu_in2 [31:0] $end
$var reg 32 S if_id_inst [31:0] $end
$var reg 1 T if_id_valid $end
$scope module u_alu $end
$var wire 32 U b [31:0] $end
$var wire 4 V opcode [3:0] $end
$var wire 1 O zero $end
$var wire 32 W a [31:0] $end
$var reg 32 X result [31:0] $end
$upscope $end
$scope module u_dec $end
$var wire 32 Y instruction [31:0] $end
$var wire 5 Z shamt [4:0] $end
$var wire 5 [ rs2 [4:0] $end
$var wire 5 \ rs1 [4:0] $end
$var wire 5 ] rd [4:0] $end
$var wire 7 ^ opcode [6:0] $end
$var wire 32 _ imm_i [31:0] $end
$var wire 7 ` funct7 [6:0] $end
$var wire 3 a funct3 [2:0] $end
$upscope $end
$scope module u_fetch $end
$var wire 1 ' clk $end
$var wire 32 b imem_req_addr [31:0] $end
$var wire 1 c imem_req_fire $end
$var wire 1 ( imem_req_ready $end
$var wire 1 " imem_req_valid $end
$var wire 32 d imem_resp_data [31:0] $end
$var wire 1 e imem_resp_fire $end
$var wire 1 ! imem_resp_ready $end
$var wire 1 * imem_resp_valid $end
$var wire 1 - reset_n $end
$var wire 32 f pc_current [31:0] $end
$var reg 1 g imem_outstanding $end
$upscope $end
$scope module u_pc $end
$var wire 1 ' clk $end
$var wire 1 < pc_en $end
$var wire 32 h pc_next [31:0] $end
$var wire 1 - reset_n $end
$var reg 32 i pc_current [31:0] $end
$upscope $end
$scope module u_rf $end
$var wire 1 ' clk $end
$var wire 5 j raddr1 [4:0] $end
$var wire 5 k raddr2 [4:0] $end
$var wire 5 l waddr [4:0] $end
$var wire 32 m wdata [31:0] $end
$var wire 1 ? we $end
$var reg 32 n rdata1 [31:0] $end
$var reg 32 o rdata2 [31:0] $end
$upscope $end
$upscope $end
$upscope $end
$enddefinitions $end
#0
$dumpvars
bx o
bx n
b0 m
bx l
bx k
bx j
bx i
bx h
xg
bx f
0e
b0 d
xc
bx b
bx a
bx `
bx _
bx ^
bx ]
bx \
bx [
bx Z
bx Y
b0 X
bx W
b0xx V
bx U
xT
bx S
bx R
b0xx Q
b0 P
1O
bx N
bx M
bx L
bx K
xJ
xI
bx H
bx G
bx F
bx E
bx D
bx C
bx B
bx A
bx @
x?
bx >
b0 =
0<
x;
x:
x9
x8
x7
06
b0 5
x4
x3
bx 2
bx 1
bx 0
x/
b100000000 .
0-
bx ,
x+
0*
b0 )
1(
0'
bx &
bx %
bx $
bx #
x"
1!
$end
#5000
b0 Q
b0 V
03
0:
09
07
b0 R
b0 U
1c
14
08
b0 A
b0 o
b0 C
b0 W
b0 n
0;
1"
0J
0I
b0 H
b0 ^
b0 >
b0 l
b0 E
b0 ]
b0 N
b0 a
b0 D
b0 \
b0 j
b0 B
b0 [
b0 k
b0 M
b0 `
b0 K
b0 _
b0 @
b0 Z
0?
b0 #
b0 L
b0 b
b100 F
b100 h
b0 G
b0 f
b0 i
0g
b0 S
b0 Y
0/
0T
b0 ,
0+
1'
#10000
0'
#15000
1'
#20000
0'
#25000
1'
#30000
0'
#31000
1-
b0 $
b0 2
b0 %
b0 1
b0 &
b0 0
b100000 .
#35000
0c
04
0"
1+
1g
1'
#40000
0'
#45000
1<
16
1e
0+
b10100000000000010010011 )
b10100000000000010010011 5
b10100000000000010010011 d
1*
1'
#50000
0'
#55000
1?
0O
b101 =
b101 m
b101 P
b101 X
13
b101 R
b101 U
18
1c
14
0<
06
0e
1J
b10011 H
b10011 ^
b1 >
b1 l
b1 E
b1 ]
b101 B
b101 [
b101 k
b101 K
b101 _
b101 @
b101 Z
1"
0*
1/
1T
b10100000000000010010011 S
b10100000000000010010011 Y
0g
b100 #
b100 L
b100 b
b1000 F
b1000 h
b100 G
b100 f
b100 i
1'
#60000
0'
#65000
0c
04
0"
0?
1g
b101 &
b101 0
0/
0T
b100 ,
1+
1'
#70000
0'
#75000
1<
16
1e
0+
b11100000000000100010011 )
b11100000000000100010011 5
b11100000000000100010011 d
1*
1'
#80000
0'
#85000
b111 =
b111 m
b111 P
b111 X
1c
14
b111 R
b111 U
1"
1?
b10 >
b10 l
b10 E
b10 ]
b111 B
b111 [
b111 k
b111 K
b111 _
b111 @
b111 Z
0<
06
0e
b1000 #
b1000 L
b1000 b
b1100 F
b1100 h
b1000 G
b1000 f
b1000 i
0g
1/
1T
b11100000000000100010011 S
b11100000000000100010011 Y
0*
1'
#90000
0'
#95000
0c
04
0?
0"
b1000 ,
1+
0/
0T
b111 %
b111 1
1g
1'
#100000
0'
#105000
1<
16
1e
0+
b1000001000000110110011 )
b1000001000000110110011 5
b1000001000000110110011 d
1*
1'
#110000
0'
#115000
b1100 =
b1100 m
b1100 P
b1100 X
13
17
08
b111 A
b111 o
b101 C
b101 W
b101 n
b111 R
b111 U
1c
14
0<
06
0e
1?
0J
1I
b110011 H
b110011 ^
b11 >
b11 l
b11 E
b11 ]
b1 D
b1 \
b1 j
b10 B
b10 [
b10 k
b10 K
b10 _
b10 @
b10 Z
1"
0*
1/
1T
b1000001000000110110011 S
b1000001000000110110011 Y
0g
b1100 #
b1100 L
b1100 b
b10000 F
b10000 h
b1100 G
b1100 f
b1100 i
1'
#120000
0'
#125000
0c
04
0"
0?
1g
b1100 $
b1100 2
0/
0T
b1100 ,
1+
1'
#130000
0'
#135000
1<
16
1e
0+
b10011 )
b10011 5
b10011 d
1*
1'
#140000
0'
#145000
1O
07
b0 R
b0 U
b0 =
b0 m
b0 P
b0 X
1c
14
18
b0 A
b0 o
b0 C
b0 W
b0 n
1"
1?
1J
0I
b10011 H
b10011 ^
b0 >
b0 l
b0 E
b0 ]
b0 D
b0 \
b0 j
b0 B
b0 [
b0 k
b0 K
b0 _
b0 @
b0 Z
0<
06
0e
b10000 #
b10000 L
b10000 b
b10100 F
b10100 h
b10000 G
b10000 f
b10000 i
0g
1/
1T
b10011 S
b10011 Y
0*
1'
#150000
0'
#155000
0c
04
0?
0"
b10000 ,
1+
0/
0T
1g
1'
#160000
0'
#165000
1<
16
1e
0+
1*
1'
#170000
0'
#175000
1c
14
0<
06
0e
1?
1"
0*
1/
1T
0g
b10100 #
b10100 L
b10100 b
b11000 F
b11000 h
b10100 G
b10100 f
b10100 i
1'
#180000
0'
#185000
0c
04
0"
0?
1g
0/
0T
b10100 ,
1+
1'
#190000
0'
#195000
1<
16
1e
0+
1*
1'
#200000
0'
#205000
1c
14
1"
1?
0<
06
0e
b11000 #
b11000 L
b11000 b
b11100 F
b11100 h
b11000 G
b11000 f
b11000 i
0g
1/
1T
0*
1'
#210000
0'
#215000
0c
04
0?
0"
b11000 ,
1+
0/
0T
1g
1'
#220000
0'
#225000
1<
16
1e
0+
1*
1'
#230000
0'
#235000
1c
14
0<
06
0e
1?
1"
0*
1/
1T
0g
b11100 #
b11100 L
b11100 b
b100000 F
b100000 h
b11100 G
b11100 f
b11100 i
1'
#240000
0'
#245000
0c
04
0"
0?
1g
0/
0T
b11100 ,
1+
1'
#250000
0'
#255000
1<
16
1e
0+
1*
1'
#260000
0'
#265000
1c
14
1"
1?
0<
06
0e
b100000 #
b100000 L
b100000 b
b100100 F
b100100 h
b100000 G
b100000 f
b100000 i
0g
1/
1T
0*
1'
#270000
0'
#275000
0c
04
0?
0"
b100000 ,
1+
0/
0T
1g
1'
#280000
0'
#285000
1<
16
1e
0+
1*
1'
#290000
0'
#295000
1c
14
0<
06
0e
1?
1"
0*
1/
1T
0g
b100100 #
b100100 L
b100100 b
b101000 F
b101000 h
b100100 G
b100100 f
b100100 i
1'
#300000
0'
#305000
0c
04
0"
0?
1g
0/
0T
b100100 ,
1+
1'
#310000
0'
#315000
1<
16
1e
0+
1*
1'
#320000
0'
#325000
1c
14
1"
1?
0<
06
0e
b101000 #
b101000 L
b101000 b
b101100 F
b101100 h
b101000 G
b101000 f
b101000 i
0g
1/
1T
0*
1'
#330000
0'
#335000
0c
04
0?
0"
b101000 ,
1+
0/
0T
1g
1'
#340000
0'
#345000
1<
16
1e
0+
1*
1'
#350000
0'
#355000
1c
14
0<
06
0e
1?
1"
0*
1/
1T
0g
b101100 #
b101100 L
b101100 b
b110000 F
b110000 h
b101100 G
b101100 f
b101100 i
1'
#360000
0'
#365000
0c
04
0"
0?
1g
0/
0T
b101100 ,
1+
1'
#370000
0'
#375000
1<
16
1e
0+
1*
1'
#380000
0'
#385000
1c
14
1"
1?
0<
06
0e
b110000 #
b110000 L
b110000 b
b110100 F
b110100 h
b110000 G
b110000 f
b110000 i
0g
1/
1T
0*
1'
#390000
0'
#395000
0c
04
0?
0"
b110000 ,
1+
0/
0T
1g
1'
#400000
0'
#405000
1<
16
1e
0+
1*
1'
#410000
0'
#415000
1c
14
0<
06
0e
1?
1"
0*
1/
1T
0g
b110100 #
b110100 L
b110100 b
b111000 F
b111000 h
b110100 G
b110100 f
b110100 i
1'
#420000
0'
#425000
0c
04
0"
0?
1g
0/
0T
b110100 ,
1+
1'
#430000
0'
#435000
1<
16
1e
0+
1*
1'
#440000
0'
#445000
1c
14
1"
1?
0<
06
0e
b111000 #
b111000 L
b111000 b
b111100 F
b111100 h
b111000 G
b111000 f
b111000 i
0g
1/
1T
0*
1'
#450000
0'
#455000
0c
04
0?
0"
b111000 ,
1+
0/
0T
1g
1'
#460000
0'
#465000
1<
16
1e
0+
1*
1'
#470000
0'
#475000
1c
14
0<
06
0e
1?
1"
0*
1/
1T
0g
b111100 #
b111100 L
b111100 b
b1000000 F
b1000000 h
b111100 G
b111100 f
b111100 i
1'
#480000
0'
#485000
0c
04
0"
0?
1g
0/
0T
b111100 ,
1+
1'
#490000
0'
#495000
1<
16
1e
0+
1*
1'
#500000
0'
#505000
1c
14
1"
1?
0<
06
0e
b1000000 #
b1000000 L
b1000000 b
b1000100 F
b1000100 h
b1000000 G
b1000000 f
b1000000 i
0g
1/
1T
0*
1'
#510000
0'
#515000
0c
04
0?
0"
b1000000 ,
1+
0/
0T
1g
1'
#520000
0'
#525000
1<
16
1e
0+
1*
1'
#530000
0'
#535000
1c
14
0<
06
0e
1?
1"
0*
1/
1T
0g
b1000100 #
b1000100 L
b1000100 b
b1001000 F
b1001000 h
b1000100 G
b1000100 f
b1000100 i
1'
#540000
0'
#545000
0c
04
0"
0?
1g
0/
0T
b1000100 ,
1+
1'
#550000
0'
#555000
1<
16
1e
0+
1*
1'
#560000
0'
#565000
1c
14
1"
1?
0<
06
0e
b1001000 #
b1001000 L
b1001000 b
b1001100 F
b1001100 h
b1001000 G
b1001000 f
b1001000 i
0g
1/
1T
0*
1'
#570000
0'
#575000
0c
04
0?
0"
b1001000 ,
1+
0/
0T
1g
1'
#580000
0'
#585000
1<
16
1e
0+
1*
1'
#590000
0'
#595000
1c
14
0<
06
0e
1?
1"
0*
1/
1T
0g
b1001100 #
b1001100 L
b1001100 b
b1010000 F
b1010000 h
b1001100 G
b1001100 f
b1001100 i
1'
#600000
0'
#605000
0c
04
0"
0?
1g
0/
0T
b1001100 ,
1+
1'
#610000
0'
#615000
1<
16
1e
0+
1*
1'
#620000
0'
#625000
1c
14
1"
1?
0<
06
0e
b1010000 #
b1010000 L
b1010000 b
b1010100 F
b1010100 h
b1010000 G
b1010000 f
b1010000 i
0g
1/
1T
0*
1'
#630000
0'
#635000
0c
04
0?
0"
b1010000 ,
1+
0/
0T
1g
1'
#640000
0'
#645000
1<
16
1e
0+
1*
1'
#650000
0'
#655000
1c
14
0<
06
0e
1?
1"
0*
1/
1T
0g
b1010100 #
b1010100 L
b1010100 b
b1011000 F
b1011000 h
b1010100 G
b1010100 f
b1010100 i
1'
#660000
0'
#665000
0c
04
0"
0?
1g
0/
0T
b1010100 ,
1+
1'
#670000
0'
#675000
1<
16
1e
0+
1*
1'
#680000
0'
#685000
1c
14
1"
1?
0<
06
0e
b1011000 #
b1011000 L
b1011000 b
b1011100 F
b1011100 h
b1011000 G
b1011000 f
b1011000 i
0g
1/
1T
0*
1'
#690000
0'
#695000
0c
04
0?
0"
b1011000 ,
1+
0/
0T
1g
1'
#700000
0'
#705000
1<
16
1e
0+
1*
1'
#710000
0'
#715000
1c
14
0<
06
0e
1?
1"
0*
1/
1T
0g
b1011100 #
b1011100 L
b1011100 b
b1100000 F
b1100000 h
b1011100 G
b1011100 f
b1011100 i
1'
#720000
0'
#725000
0c
04
0"
0?
1g
0/
0T
b1011100 ,
1+
1'
